{
  "connecte": true,
  "source": "meta-graph-api",
  "maj": "2026-06-23T03:35:35+00:00",
  "global": {
    "audience": 24642,
    "posts": 25,
    "likes": 751,
    "commentaires": 32,
    "partages": null,
    "portee": null,
    "engagement_taux": null
  },
  "par_reseau": {
    "facebook": {
      "abonnes": 24642,
      "posts": 25,
      "likes": 751,
      "commentaires": 32,
      "portee": null
    },
    "instagram": {
      "abonnes": null,
      "posts": null,
      "likes": null,
      "commentaires": null,
      "portee": null
    },
    "tiktok": {
      "abonnes": null,
      "posts": null,
      "likes": null,
      "commentaires": null,
      "portee": null
    },
    "linkedin": {
      "abonnes": null,
      "posts": null,
      "likes": null,
      "commentaires": null,
      "portee": null
    }
  },
  "top_fans": [],
  "top_posts": [
    {
      "titre": "Que peut-on dire quand les photos parlent d’elle-même ?😊￼ voici la meilleure Ten",
      "plateforme": "Facebook",
      "likes": 176,
      "commentaires": 5,
      "partages": 47
    },
    {
      "titre": "Plus que quelques heures 😏🤗\n\nMacky sall 3 pièces en couple disponible \n\nPrix: 1.",
      "plateforme": "Facebook",
      "likes": 104,
      "commentaires": 0,
      "partages": 26
    },
    {
      "titre": "Macky sall 3 pièces disponible actuellement\nDe la taille L à XL\n\nEn gros 6M500 à",
      "plateforme": "Facebook",
      "likes": 95,
      "commentaires": 1,
      "partages": 14
    },
    {
      "titre": "Le couturier a raté ton basin?\nIl t’a donné faux rdv ? Yako \nViens prendre ton m",
      "plateforme": "Facebook",
      "likes": 79,
      "commentaires": 0,
      "partages": 22
    },
    {
      "titre": "Sinon à la base skinny même c’est femme de milliardaire oubien 😌😏\nOù sont mes pe",
      "plateforme": "Facebook",
      "likes": 71,
      "commentaires": 0,
      "partages": 11
    },
    {
      "titre": "À la demande générale 🥰😍👌￼ \nnous avons stocké nos Lingerie de Qualité.\nDisponibl",
      "plateforme": "Facebook",
      "likes": 58,
      "commentaires": 2,
      "partages": 23
    },
    {
      "titre": "ML KOUYATE  ramène mon argent ..\n\nIl a acheté un Article vers 17 heures et a ann",
      "plateforme": "Facebook",
      "likes": 27,
      "commentaires": 23,
      "partages": 50
    },
    {
      "titre": "String  chap chap et lingerie fine disponible actuellement \n\nPrix: 3 string à 10",
      "plateforme": "Facebook",
      "likes": 33,
      "commentaires": 0,
      "partages": 12
    }
  ],
  "evolution_audience": [],
  "client": "merveille-boutik"
}